indoorloc/__init__.py
indoorloc/registry.py
indoorloc/version.py
indoorloc/configs/__init__.py
indoorloc/configs/_base_/default.yaml
indoorloc/configs/_base_/datasets/sodindoorloc.yaml
indoorloc/configs/_base_/datasets/tampere.yaml
indoorloc/configs/_base_/datasets/ujindoorloc.yaml
indoorloc/configs/_base_/models/cnn1d.yaml
indoorloc/configs/_base_/models/knn.yaml
indoorloc/configs/_base_/models/mlp.yaml
indoorloc/configs/_base_/models/resnet.yaml
indoorloc/configs/_base_/models/wknn.yaml
indoorloc/configs/_base_/schedules/schedule_1x.yaml
indoorloc/configs/_base_/schedules/schedule_2x.yaml
indoorloc/configs/wifi/efficientnet_ujindoorloc.yaml
indoorloc/configs/wifi/knn_ujindoorloc.yaml
indoorloc/configs/wifi/mlp_ujindoorloc.yaml
indoorloc/configs/wifi/resnet18_ujindoorloc.yaml
indoorloc/configs/wifi/resnet18_ujindoorloc_annotated.yaml
indoorloc/configs/wifi/resnet18_ujindoorloc_minimal.yaml
indoorloc/configs/wifi/wknn_ujindoorloc.yaml
indoorloc/datasets/__init__.py
indoorloc/datasets/base.py
indoorloc/datasets/ble_indoor.py
indoorloc/datasets/ble_rssi_uci.py
indoorloc/datasets/catalog.py
indoorloc/datasets/csi2pos.py
indoorloc/datasets/csi2taoa.py
indoorloc/datasets/csi_bench.py
indoorloc/datasets/csi_fingerprint.py
indoorloc/datasets/csi_indoor.py
indoorloc/datasets/csu_csi_rssi.py
indoorloc/datasets/deepmimo.py
indoorloc/datasets/dichasus.py
indoorloc/datasets/espargos.py
indoorloc/datasets/haloc.py
indoorloc/datasets/hwild.py
indoorloc/datasets/ibeacon_rssi.py
indoorloc/datasets/loading.py
indoorloc/datasets/longtermwifi.py
indoorloc/datasets/magnetic_indoor.py
indoorloc/datasets/mamimo_csi.py
indoorloc/datasets/mamimo_uav.py
indoorloc/datasets/multimodal_indoor.py
indoorloc/datasets/opencsi.py
indoorloc/datasets/rfid_indoor.py
indoorloc/datasets/rss_based.py
indoorloc/datasets/sensor_fusion.py
indoorloc/datasets/sodindoorloc.py
indoorloc/datasets/tampere.py
indoorloc/datasets/tuji1.py
indoorloc/datasets/ujindoorloc.py
indoorloc/datasets/ultrasound_indoor.py
indoorloc-0.1.3.dist-info/licenses/LICENSE
indoorloc-0.1.3.dist-info/METADATA
indoorloc-0.1.3.dist-info/WHEEL
indoorloc-0.1.3.dist-info/entry_points.txt
indoorloc-0.1.3.dist-info/top_level.txt
indoorloc-0.1.3.dist-info/RECORD
