Metadata-Version: 2.4
Name: indoorloc
Version: 0.1.3
Summary: A unified framework for indoor localization
Author: IndoorLoc Team
Maintainer: IndoorLoc Team
License: Apache-2.0
Project-URL: Homepage, https://github.com/indoorloc/indoorloc
Project-URL: Documentation, https://indoorloc.readthedocs.io
Project-URL: Repository, https://github.com/indoorloc/indoorloc
Project-URL: Issues, https://github.com/indoorloc/indoorloc/issues
Keywords: indoor localization,WiFi fingerprinting,positioning,deep learning,machine learning,location,RSSI
Classifier: Development Status :: 3 - Alpha
Classifier: Intended Audience :: Developers
Classifier: Intended Audience :: Science/Research
Classifier: License :: OSI Approved :: Apache Software License
Classifier: Operating System :: OS Independent
Classifier: Programming Language :: Python :: 3
Classifier: Programming Language :: Python :: 3.8
Classifier: Programming Language :: Python :: 3.9
Classifier: Programming Language :: Python :: 3.10
Classifier: Programming Language :: Python :: 3.11
Classifier: Programming Language :: Python :: 3.12
Classifier: Topic :: Scientific/Engineering :: Artificial Intelligence
Classifier: Topic :: Scientific/Engineering :: Information Analysis
Requires-Python: >=3.8
License-File: LICENSE
Requires-Dist: torch>=1.10.0
Requires-Dist: numpy>=1.20.0
Requires-Dist: pandas>=1.3.0
Requires-Dist: scikit-learn>=1.0.0
Requires-Dist: pyyaml>=6.0
Requires-Dist: tqdm>=4.60.0
Provides-Extra: datasets
Requires-Dist: h5py>=3.0.0; extra == "datasets"
Requires-Dist: scipy>=1.7.0; extra == "datasets"
Requires-Dist: requests>=2.25.0; extra == "datasets"
Provides-Extra: vision
Requires-Dist: torchvision>=0.11.0; extra == "vision"
Requires-Dist: opencv-python>=4.5.0; extra == "vision"
Provides-Extra: deep
Requires-Dist: timm>=0.9.0; extra == "deep"
Provides-Extra: deepmimo
Requires-Dist: DeepMIMO>=4.0.0b5; extra == "deepmimo"
Provides-Extra: full
Requires-Dist: torchvision>=0.11.0; extra == "full"
Requires-Dist: opencv-python>=4.5.0; extra == "full"
Requires-Dist: matplotlib>=3.4.0; extra == "full"
Requires-Dist: seaborn>=0.11.0; extra == "full"
Requires-Dist: scipy>=1.7.0; extra == "full"
Requires-Dist: h5py>=3.0.0; extra == "full"
Requires-Dist: requests>=2.25.0; extra == "full"
Requires-Dist: timm>=0.9.0; extra == "full"
Provides-Extra: dev
Requires-Dist: pytest>=7.0.0; extra == "dev"
Requires-Dist: pytest-cov>=3.0.0; extra == "dev"
Requires-Dist: black>=22.0.0; extra == "dev"
Requires-Dist: flake8>=4.0.0; extra == "dev"
Requires-Dist: isort>=5.10.0; extra == "dev"
Requires-Dist: mypy>=0.950; extra == "dev"
Provides-Extra: docs
Requires-Dist: sphinx>=4.0.0; extra == "docs"
Requires-Dist: sphinx-rtd-theme>=1.0.0; extra == "docs"
Requires-Dist: myst-parser>=0.18.0; extra == "docs"
Dynamic: license-file
